Workbook

Sheet Inputs
A1: Token Cost Calculator
A2: Enter your workload in the blue cells. All monetary results are shown in USD.
A4: 1. Workload volume
A5: Transactions per month | B5: 50000 | C5: transactions | D5: Use successful and unsuccessful requests if both are billable under the vendor terms.
A7: 2. Token shape per transaction
A8: Input tokens per transaction | B8: 8100 | C8: tokens | D8: Everything sent to the model, including instructions, retrieved content, conversation history, and tool definitions.
A9: Output tokens per transaction | B9: 400 | C9: tokens | D9: The visible answer returned by the model.
A10: Reasoning tokens per transaction | B10: 0 | C10: tokens | D10: Internal working tokens. Default to zero only if the vendor confirms none are billed. They are often substantial.
A12: 3. Vendor token rates
A13: Input rate | B13: 3 | C13: USD per million tokens | D13: Replace the illustrative rate with the quoted rate for the exact model and endpoint.
A14: Output rate | B14: 15 | C14: USD per million tokens | D14: Reasoning tokens are costed at this rate. Confirm that treatment with the vendor.
A16: 4. Architecture and commercial modifiers
A17: Input tokens served from cache | B17: 0 | C17: % of input tokens | D17: Enter the share of input tokens expected to hit a valid cache, not the share of transactions using a cache.
A18: Cached input rate | B18: 0.1 | C18: % of standard input rate | D18: Illustrative default is 10%. Verify the vendor's cache read rate, write cost, expiry, and eligibility rules.
A19: Volume eligible for batch processing | B19: 0 | C19: % of transactions | D19: Batching usually requires delayed processing. Enter only the volume that can meet the vendor's turnaround conditions.
A20: Batch discount on eligible volume | B20: 0.5 | C20: % off | D20: Illustrative default is 50%. Confirm the discount and whether it stacks with caching.
A21: Regional or residency uplift | B21: 0 | C21: % added | D21: Enter any uplift for a named region, data residency, or specialized endpoint. Default is zero.
A23: Default scenario: the budgeted policy chatbot example. Enter 2,000 reasoning tokens to see monthly cost rise from USD 1,515 to USD 3,015.

Sheet Results
A1: Token Cost Results
A2: Formula driven from the Inputs sheet. Do not type on this sheet.
A4: MONTHLY COST | D4: ANNUAL COST | G4: COST PER TRANSACTION
A5: =SUM(B11:B13) -> 1515 | D5: =A5*12 -> 18180 | G5: =IF(Inputs!$B$5=0,0,A5/Inputs!$B$5) -> 0.0303
A8: Cost breakdown
A10: Component | B10: Monthly cost | C10: Annual cost | D10: Share of total
A11: Input | B11: =(Inputs!$B$5*Inputs!$B$8/1000000*Inputs!$B$13*((1-Inputs!$B$17)+(Inputs!$B$17*Inputs!$B$18)))*(1-Inputs!$B$19*Inputs!$B$20)*(1+Inputs!$B$21) -> 1215 | C11: =B11*12 -> 14580 | D11: =IF($B$14=0,0,B11/$B$14) -> 0.8019802
A12: Visible output | B12: =(Inputs!$B$5*Inputs!$B$9/1000000*Inputs!$B$14)*(1-Inputs!$B$19*Inputs!$B$20)*(1+Inputs!$B$21) -> 300 | C12: =B12*12 -> 3600 | D12: =IF($B$14=0,0,B12/$B$14) -> 0.1980198
A13: Reasoning | B13: =(Inputs!$B$5*Inputs!$B$10/1000000*Inputs!$B$14)*(1-Inputs!$B$19*Inputs!$B$20)*(1+Inputs!$B$21) -> 0 | C13: =B13*12 -> 0 | D13: =IF($B$14=0,0,B13/$B$14) -> 0
A14: Total | B14: =SUM(B11:B13) -> 1515 | C14: =B14*12 -> 18180 | D14: =IF($B$14=0,0,SUM(D11:D13)) -> 1
A16: Cost with and without caching and batching
A18: Without optimization | C18: With current assumptions | E18: Monthly saving | G18: Saving rate
A19: =(Inputs!$B$5*Inputs!$B$8/1000000*Inputs!$B$13)*(1+Inputs!$B$21)+(Inputs!$B$5*Inputs!$B$9/1000000*Inputs!$B$14)*(1+Inputs!$B$21)+(Inputs!$B$5*Inputs!$B$10/1000000*Inputs!$B$14)*(1+Inputs!$B$21) -> 1515 | C19: =$B$14 -> 1515 | E19: =MAX(0,A19-C19) -> 0 | G19: =IF(A19=0,0,E19/A19) -> 0
A22: Volume sensitivity
A24: Scenario | B24: Volume multiplier | C24: Transactions | D24: Monthly cost | E24: Annual cost
A25: Half volume | B25: 0.5 | C25: =Inputs!$B$5*B25 -> 25000 | D25: =$B$14*B25 -> 757.5 | E25: =D25*12 -> 9090
A26: Current volume | B26: 1 | C26: =Inputs!$B$5*B26 -> 50000 | D26: =$B$14*B26 -> 1515 | E26: =D26*12 -> 18180
A27: Triple volume | B27: 3 | C27: =Inputs!$B$5*B27 -> 150000 | D27: =$B$14*B27 -> 4545 | E27: =D27*12 -> 54540
A29: Procurement challenge: any vendor forecast quoting one tokens per month number is useless. Send it back and ask for the input, output, and reasoning split.

Sheet Notes
A1: Notes, Assumptions, and Sources
A2: Rates move quickly. Verify every rate and modifier against vendor documentation before using the result in a business case.
A4: How to use the calculator
A5: 1 | B5: Replace the example workload on the Inputs sheet with the vendor's input, visible output, and reasoning token forecast.
A6: 2 | B6: Replace the illustrative token rates and commercial modifiers with the rates for the exact model, endpoint, and contract.
A7: 3 | B7: Review the Results sheet, including the component split, optimization saving, and volume sensitivity.
A8: 4 | B8: Return any forecast that provides only one total token volume. The split determines the cost.
A10: Calculation logic
A11: Input cost | B11: Input volume × input rate, adjusted for the share served from cache.
A12: Output cost | B12: Visible output volume × output rate.
A13: Reasoning cost | B13: Reasoning token volume × output rate.
A14: Batch factor | B14: 1 minus eligible batch volume multiplied by the batch discount. Applied to input, output, and reasoning.
A15: Residency factor | B15: 1 plus the regional or residency uplift. Applied after caching and batching.
A17: Rate and assumption register
A19: Item | B19: Loaded value | C19: As at | D19: What to verify
A20: Input rate | B20: $3 per million tokens | C20: July 2026 | D20: Exact model, endpoint, currency, volume tier, and contracted rate.
A21: Output and reasoning rate | B21: $15 per million tokens | C21: July 2026 | D21: Output rate and whether all internal reasoning tokens are billable.
A22: Cached input rate | B22: 10% of standard input rate | C22: July 2026 | D22: Cache read price, write cost, expiry, minimum prefix, and stacking rules.
A23: Batch discount | B23: 50% on eligible volume | C23: July 2026 | D23: Turnaround, eligibility, service level, and whether the discount stacks with caching.
A24: Regional or residency uplift | B24: 0% loaded, about 10% illustrated | C24: July 2026 | D24: Exact endpoint uplift and whether it applies to every meter.
A26: RATES AND CURRENCY
A27: All rates are entered by you on the Inputs sheet. Nothing is hard coded into a formula, so this calculator does not go stale. Update the rate cells whenever the market moves.
A28: The example values shipped with this file reflect representative production tier pricing as at July 2026. Model lineups and token rates move quickly. Verify against the vendor's own published rate card before any figure from this sheet enters a business case.
A29: Rates are quoted in United States dollars. If you are budgeting in another currency, apply your own exchange assumption and state it.
A31: HOW THE CALCULATION WORKS
A32: Input cost blends cached and uncached input. The uncached share is billed at the full input rate. The cached share is billed at the cached multiplier, which is roughly ten percent across major vendors.
A33: Output cost is the output token volume at the output rate. Output typically costs five to six times input.
A34: Reasoning tokens are billed at the OUTPUT rate, not the input rate. This is the single most commonly missed item in an AI cost forecast.
A35: The batch discount is applied to the share of volume you mark as batch eligible, across all three meters.
A36: The regional uplift is applied last, to the whole bill.
A38: GETTING YOUR TOKEN NUMBERS
A39: Do not accept a vendor forecast that quotes a single tokens per month figure. Ask for the split into input, output, and reasoning tokens for your workload.
... A54: Source and version
A55: Calculator | B55: token-cost-calculator.xlsx, version 1.0
A56: Toolkit release | B56: 0.2.0, prepared 2026-07-31
A57: Repository | B57: https://github.com/arunbalajiraju-proc/ai-procurement-toolkit
A59: Part of the ai-procurement-toolkit. The toolkit works with any assistant, and this calculator opens in any modern spreadsheet application. This is a procurement and commercial tool, not legal advice.
